hardware/simple/dmem.v
`include "def.h"
module dmem (
 input clk,
 input [15:0] a,
 output [`DATA_W-1:0] rd,
 input [`DATA_W-1:0] wd,
 input  we);

	reg [`DATA_W-1:0] mem[0:`DEPTH-1];

	assign rd = mem[a];

	always @(posedge clk)  begin
		if(we) mem[a] <= wd;
	end
	initial
      begin
           $readmemh("dmem.dat", mem);
    end
endmodule

hardware/simple/imem.v
`include "def.h"
module imem (
 input [15:0] a,
 output [`DATA_W-1:0] rd);

	reg [`DATA_W-1:0] mem[0:`DEPTH-1];

	assign rd = mem[a];

	initial begin
           $readmemh("imem.dat", mem);
    end

endmodule

hardware/mips0717/rfile.v
`include "def.h"
module rfile (
 input clk,
 input [`REG_W-1:0] a1, a2, a3,
 output [`DATA_W-1:0] rd1, rd2,
 input [`DATA_W-1:0] wd3,
 input we3);

	reg [`DATA_W-1:0] rf[0:`REG-1];

	assign rd1 = |a1 == 0 ? 0: rf[a1];
	assign rd2 = |a2 == 0 ? 0: rf[a2];

	always @(posedge clk) 
		if(we3) rf[a3] <= wd3;

endmodule

hardware/simple/alu.v
`include "def.h"

module alu (
  input [`DATA_W-1:0] a, b, 
  input [`SEL_W-1:0] s,
  output [`DATA_W-1:0] y,
  output zero );
  assign y = s==`ALU_ADD ? a+b:
  			 s==`ALU_SUB ? a-b:
             s==`ALU_AND ? a & b:
             s==`ALU_OR ? a | b:
             s==`ALU_XOR ? a ^ b:
             s==`ALU_NOR ? ~ (a | b): b;
  assign zero = (y == 32'b0);
endmodule

hardware/simple/mipse.v
`include "def.h"
module mipse(
input clk, rst_n,
input [`DATA_W-1:0] instr,
input [`DATA_W-1:0] readdata,
output reg [`DATA_W-1:0] pc, 
output [`DATA_W-1:0] aluresult,
output [`DATA_W-1:0] writedata,
output memwrite);

wire [`DATA_W-1:0] srca, srcb, result;
wire [`OPCODE_W-1:0] opcode;
wire [`SHAMT_W-1:0] shamt;
wire [`OPCODE_W-1:0] func;
wire [`REG_W-1:0] rs, rd, rt, writereg;
wire [`SEL_W-1:0] com;
wire [`DATA_W-1:0] signimm;
wire [`DATA_W-1:0] pcplus4;
wire regwrite;
wire sw_op, beq_op, bne_op, addi_op, lw_op, j_op, alu_op;
wire zero;

assign {opcode, rs, rt, rd, shamt, func} = instr;
assign signimm = {{16{instr[15]}},instr[15:0]};

// Decorder
assign sw_op = (opcode == `OP_SW);
assign lw_op = (opcode == `OP_LW);
assign alu_op = (opcode == `OP_REG) & (func[5:3] == 3'b100);
assign addi_op = (opcode == `OP_ADDI);
assign beq_op = (opcode == `OP_BEQ);
assign bne_op = (opcode == `OP_BNE);
assign j_op = (opcode == `OP_J);
assign memwrite = sw_op;

assign srcb = (addi_op | lw_op | sw_op ) ? 
								signimm : writedata;

assign com = (addi_op|lw_op|sw_op) ? `ALU_ADD: 
			(beq_op | bne_op) ? `ALU_SUB: func;

assign result = lw_op  ? readdata : aluresult;

assign regwrite = lw_op | alu_op | addi_op ;

assign writereg = alu_op ? rd : rt;

alu alu_1(.a(srca), .b(srcb), .s(com), .y(aluresult), .zero(zero));

rfile rfile_1(.clk(clk), .rd1(srca), .a1(rs), .rd2(writedata), .a2(rt), 
	.wd3(result), .a3(writereg), .we3(regwrite));

assign pcplus4 = pc+4;
always @(posedge clk or negedge rst_n) 
begin 
   if(!rst_n) pc <= 0;
   else if (j_op) 
   	 pc	<= {pc[31:28],instr[25:0],2'b0};
   else if ((beq_op & zero) | (bne_op & !zero))
     pc <= pcplus4 +{signimm[29:0],2'b0} ;
   else 
     pc <= pcplus4;
end

endmodule

hardware/simple/test_mipse.v
/* test bench */
`timescale 1ns/1ps
`include "def.h"
module test_mipse;
parameter STEP = 10;
   reg clk, rst_n;
   wire [`DATA_W-1:0] ddataout, ddatain ;
   wire [`DATA_W-1:0] iaddr;
   wire [`DATA_W-1:0] daddr;
   wire [`DATA_W-1:0] idata;
   wire we;
  
   always #(STEP/2) begin
            clk <= ~clk;
   end

   mipse mipse_1(.clk(clk), .rst_n(rst_n), .instr(idata),
               .readdata(ddatain), .pc(iaddr), .aluresult(daddr),
               .writedata(ddataout), .memwrite(we) );
  imem  imem_1(.a(iaddr[17:2]), .rd(idata) );
  dmem  dmem_1(.clk(clk), .a(daddr[17:2]), .rd(ddatain), 
  					.wd(ddataout), .we(we) );

   initial begin
      $dumpfile("mipse.vcd");
      $dumpvars(0,mipse_1);
      clk <= `DISABLE;
      rst_n <= `ENABLE_N;
   #(STEP*1/4)
   #STEP
      rst_n <= `DISABLE_N;
   #(STEP*100)
   $finish;
   end

   always @(negedge clk) begin
      $display("pc:%h idatain:%h", mipse_1.pc, mipse_1.instr);
      $display("reg:%h %h %h %h %h %h %h %h | %h", 
	mipse_1.rfile_1.rf[0], mipse_1.rfile_1.rf[1], mipse_1.rfile_1.rf[2],
	mipse_1.rfile_1.rf[3], mipse_1.rfile_1.rf[4], mipse_1.rfile_1.rf[5],
	mipse_1.rfile_1.rf[6], mipse_1.rfile_1.rf[7], mipse_1.rfile_1.rf[31]);
    $display("dmem:%h %h %h %h", dmem_1.mem[0], dmem_1.mem[1], dmem_1.mem[2], dmem_1.mem[3] );
   end 
endmodule

hardware/simple/mipse.vcd
$date
	Fri Jun  3 11:00:01 2016
$end
$version
	Icarus Verilog
$end
$timescale
	1ps
$end
$scope module test_mipse $end
$scope module mipse_1 $end
$var wire 1 ! addi_op $end
$var wire 1 " alu_op $end
$var wire 32 # aluresult [31:0] $end
$var wire 1 $ beq_op $end
$var wire 1 % bne_op $end
$var wire 1 & clk $end
$var wire 6 ' com [5:0] $end
$var wire 6 ( func [5:0] $end
$var wire 32 ) instr [31:0] $end
$var wire 1 * j_op $end
$var wire 1 + lw_op $end
$var wire 1 , memwrite $end
$var wire 6 - opcode [5:0] $end
$var wire 32 . pcplus4 [31:0] $end
$var wire 5 / rd [4:0] $end
$var wire 32 0 readdata [31:0] $end
$var wire 1 1 regwrite $end
$var wire 32 2 result [31:0] $end
$var wire 5 3 rs [4:0] $end
$var wire 1 4 rst_n $end
$var wire 5 5 rt [4:0] $end
$var wire 5 6 shamt [4:0] $end
$var wire 32 7 signimm [31:0] $end
$var wire 32 8 srca [31:0] $end
$var wire 32 9 srcb [31:0] $end
$var wire 1 : sw_op $end
$var wire 32 ; writedata [31:0] $end
$var wire 5 < writereg [4:0] $end
$var wire 1 = zero $end
$var reg 32 > pc [31:0] $end
$scope module alu_1 $end
$var wire 32 ? a [31:0] $end
$var wire 32 @ b [31:0] $end
$var wire 6 A s [5:0] $end
$var wire 32 B y [31:0] $end
$var wire 1 = zero $end
$upscope $end
$scope module rfile_1 $end
$var wire 5 C a1 [4:0] $end
$var wire 5 D a2 [4:0] $end
$var wire 5 E a3 [4:0] $end
$var wire 1 & clk $end
$var wire 32 F rd1 [31:0] $end
$var wire 32 G rd2 [31:0] $end
$var wire 32 H wd3 [31:0] $end
$var wire 1 1 we3 $end
$upscope $end
$upscope $end
$upscope $end
$enddefinitions $end
#0
$dumpvars
b11 H
bx G
b0 F
b1 E
b1 D
b0 C
b0 B
b100000 A
b0 @
b0 ?
b0 >
1=
b1 <
bx ;
0:
b0 9
b0 8
b0 7
b0 6
b1 5
04
b0 3
b11 2
11
b11 0
b0 /
b100 .
b100011 -
0,
1+
0*
b10001100000000010000000000000000 )
b0 (
b100000 '
0&
0%
0$
b0 #
0"
0!
$end
#5000
b11 ;
b11 G
1&
#10000
0&
#12000
14
#15000
b101 2
b101 H
b101 0
0=
b100 #
b100 B
b100 9
b100 @
b10 <
b10 E
bx ;
bx G
b100 7
b10 5
b10 D
b100 (
b1000 .
b10001100000000100000000000000100 )
b100 >
1&
#20000
0&
#25000
1=
b11 0
b0 #
b0 B
b0 9
b0 @
b0 2
b0 H
1"
b11 <
b11 E
b1100000100000 7
0+
b0 -
b0 5
b0 D
b11 /
b100000 (
b0 ;
b0 G
b1100 .
b1100000100000 )
b1000 >
1&
#30000
0&
#35000
b101 2
b101 H
b101 0
0=
b101 #
b101 B
b101 9
b101 @
b101 ;
b101 G
b11 3
b11 C
b10 5
b10 D
b10000 .
b11000100001100000100000 )
b1100 >
1&
#40000
0&
#45000
b11111111111111111111111111111111 9
b11111111111111111111111111111111 @
b100000 '
b100000 A
b10 2
b10 H
b11 0
0"
b11 ;
b11 G
b1 <
b1 E
b10 #
b10 B
b11111111111111111111111111111111 7
1!
b1000 -
b1 3
b1 C
b1 5
b1 D
b11111 /
b11111 6
b111111 (
b11 8
b11 ?
b11 F
b10100 .
b100000001000011111111111111111 )
b10000 >
1&
#50000
0&
#55000
b11 0
b100010 '
b100010 A
b10 2
b10 H
b0 9
b0 @
01
b0 <
b0 E
b10 #
b10 B
b11111111111111111111111111111101 7
0!
1%
b101 -
b0 5
b0 D
b111101 (
b10 8
b10 ?
b10 F
b0 ;
b0 G
b11000 .
b10100001000001111111111111101 )
b10100 >
1&
#60000
0&
#65000
bx 0
b1010 2
b1010 H
11
b100000 '
b100000 A
0=
b1010 #
b1010 B
b101 9
b101 @
1"
b101 8
b101 ?
b101 F
b11 <
b11 E
b101 ;
b101 G
b1100000100000 7
0%
b0 -
b11 3
b11 C
b10 5
b10 D
b11 /
b0 6
b100000 (
b10000 .
b11000100001100000100000 )
b1100 >
1&
#70000
0&
#75000
b11 0
b11111111111111111111111111111111 9
b11111111111111111111111111111111 @
b100000 '
b100000 A
b1 2
b1 H
0"
b10 ;
b10 G
b1 <
b1 E
b1 #
b1 B
b11111111111111111111111111111111 7
1!
b1000 -
b1 3
b1 C
b1 5
b1 D
b11111 /
b11111 6
b111111 (
b10 8
b10 ?
b10 F
b10100 .
b100000001000011111111111111111 )
b10000 >
1&
#80000
0&
#85000
b11 0
b100010 '
b100010 A
b1 2
b1 H
b0 9
b0 @
01
b0 <
b0 E
0=
b1 #
b1 B
b11111111111111111111111111111101 7
0!
1%
b101 -
b0 5
b0 D
b111101 (
b1 8
b1 ?
b1 F
b0 ;
b0 G
b11000 .
b10100001000001111111111111101 )
b10100 >
1&
#90000
0&
#95000
b1111 2
b1111 H
bx 0
11
b100000 '
b100000 A
b1111 #
b1111 B
b101 9
b101 @
1"
b1010 8
b1010 ?
b1010 F
b11 <
b11 E
b101 ;
b101 G
b1100000100000 7
0%
b0 -
b11 3
b11 C
b10 5
b10 D
b11 /
b0 6
b100000 (
b10000 .
b11000100001100000100000 )
b1100 >
1&
#100000
0&
#105000
1=
b11 0
b11111111111111111111111111111111 9
b11111111111111111111111111111111 @
b100000 '
b100000 A
b0 2
b0 H
0"
b1 ;
b1 G
b1 <
b1 E
b0 #
b0 B
b11111111111111111111111111111111 7
1!
b1000 -
b1 3
b1 C
b1 5
b1 D
b11111 /
b11111 6
b111111 (
b1 8
b1 ?
b1 F
b10100 .
b100000001000011111111111111111 )
b10000 >
1&
#110000
0&
#115000
b100010 '
b100010 A
b0 2
b0 H
b11 0
b0 9
b0 @
01
b0 <
b0 E
1=
b0 #
b0 B
b11111111111111111111111111111101 7
0!
1%
b101 -
b0 5
b0 D
b111101 (
b0 8
b0 ?
b0 F
b0 ;
b0 G
b11000 .
b10100001000001111111111111101 )
b10100 >
1&
#120000
0&
#125000
b1000 2
b1000 H
bx 0
0=
b1000 #
b1000 B
b100000 '
b100000 A
b1000 9
b1000 @
b11 <
b11 E
b1111 ;
b1111 G
b1000 7
1:
1,
0%
b101011 -
b0 3
b0 C
b11 5
b11 D
b0 /
b0 6
b1000 (
b11100 .
b10101100000000110000000000001000 )
b11000 >
1&
#130000
0&
#135000
b0 2
b0 H
1=
b0 #
b0 B
b111 '
b111 A
b0 9
b0 @
b0 <
b0 E
b0 ;
b0 G
b111 7
0:
0,
1*
b10 -
b0 5
b0 D
b111 (
b100000 .
b1000000000000000000000000111 )
b11 0
b11100 >
1&
